[
    {
        "customer_details": {
            "full_name": "John Doe",
            "phone_number": "+1234567890",
            "email": "johndoe@example.com"
        },
        "products_ordered": [
            {
                "product_name": "Running Shoes",
                "quantity": 2,
                "price_per_unit": 60
            }
        ],
        "order_address": {
            "street": "123 Main St",
            "city": "New York",
            "postal_code": "10001",
            "country": "USA"
        },
        "supplied": true
    },
    {
        "customer_details": {
            "full_name": "Alice Johnson",
            "phone_number": "+9876543210",
            "email": "alicej@example.com"
        },
        "products_ordered": [
            {
                "product_name": "Leather Boots",
                "quantity": 1,
                "price_per_unit": 120
            },
            {
                "product_name": "Sneakers",
                "quantity": 2,
                "price_per_unit": 50
            }
        ],
        "order_address": {
            "street": "789 Oak St",
            "city": "San Francisco",
            "postal_code": "94107",
            "country": "USA"
        },
        "supplied": false
    },
    {
        "customer_details": {
            "full_name": "Michael Smith",
            "phone_number": "+1122334455",
            "email": "michaelsmith@example.com"
        },
        "products_ordered": [
            {
                "product_name": "Sandals",
                "quantity": 3,
                "price_per_unit": 30
            }
        ],
        "order_address": {
            "street": "456 Maple Dr",
            "city": "Los Angeles",
            "postal_code": "90001",
            "country": "USA"
        },
        "supplied": true
    }
]
